cfbfastR/__init__.py
cfbfastR/config.py
cfbfastR/dl_utils.py
cfbfastR/errors.py
cfbfastR/cfb/__init__.py
cfbfastR/cfb/cfb_loaders.py
cfbfastR/cfb/cfb_pbp.py
cfbfastR/cfb/model_vars.py
cfbfastR/cfb/models/ep_model.model
cfbfastR/cfb/models/qbr_model.model
cfbfastR/cfb/models/wp_spread.model
cfbfastR/nfl/__init__.py
cfbfastR/nfl/nfl_loaders.py
cfbfastR_py-0.0.28.dist-info/METADATA
cfbfastR_py-0.0.28.dist-info/WHEEL
cfbfastR_py-0.0.28.dist-info/top_level.txt
cfbfastR_py-0.0.28.dist-info/RECORD
