Metadata-Version: 2.1
Name: cfbfastR-py
Version: 0.0.28
Summary: Retrieve American football data in Python
Home-page: https://github.com/saiemgilani/cfbfastR-py
Author: Saiem Gilani
Author-email: saiem.gilani@gmail.com
Maintainer: Saiem Gilani
License: MIT
Project-URL: Docs, https://cfbfastR-py.sportsdataverse.org/
Project-URL: Bug Tracker, https://github.com/saiemgilani/cfbfastR-py/issues
Keywords: nfl college football data epa statistics web scraping
Platform: UNKNOWN
Classifier: Development Status :: 3 - Alpha
Classifier: Intended Audience :: Developers
Classifier: Topic :: Software Development :: Libraries
Classifier: License :: OSI Approved :: MIT License
Classifier: Programming Language :: Python :: 3
Classifier: Programming Language :: Python :: 3.6
Classifier: Programming Language :: Python :: 3.7
Classifier: Programming Language :: Python :: 3.8
Classifier: Programming Language :: Python :: 3.9
Requires-Dist: numpy (>=1.13.0)
Requires-Dist: pandas (>=1.0.3)
Requires-Dist: beautifulsoup4 (>=4.4.0)
Requires-Dist: requests (>=2.18.1)
Requires-Dist: lxml (>=4.2.1)
Requires-Dist: pyarrow (>=1.0.1)
Requires-Dist: pygithub (>=1.51)
Requires-Dist: scipy (>=1.4.0)
Requires-Dist: matplotlib (>=2.0.0)
Requires-Dist: tqdm (>=4.50.0)
Requires-Dist: attrs (>=20.3.0)
Requires-Dist: xgboost (>=1.2.0)
Provides-Extra: test
Requires-Dist: pytest (>=6.0.2) ; extra == 'test'
Requires-Dist: mypy (>=0.782) ; extra == 'test'
Requires-Dist: pytest-cov (>=2.10.1) ; extra == 'test'
Requires-Dist: pytest-xdist (>=2.1.0) ; extra == 'test'
